hdx/location/Countries & Territories Taxonomy MVP - C&T Taxonomy.csv
hdx/location/__init__.py
hdx/location/_version.py
hdx/location/adminlevel.py
hdx/location/country.py
hdx/location/currency.py
hdx/location/int_timestamp.py
hdx/location/wfp_api.py
hdx/location/wfp_exchangerates.py
hdx_python_country-4.1.0.dist-info/METADATA
hdx_python_country-4.1.0.dist-info/WHEEL
hdx_python_country-4.1.0.dist-info/licenses/LICENSE
hdx_python_country-4.1.0.dist-info/RECORD
