Metadata-Version: 2.4
Name: hdx-python-country
Version: 4.1.0
Summary: HDX Python country code and exchange rate (fx) utilities
Project-URL: Homepage, https://github.com/OCHA-DAP/hdx-python-country
Author: Michael Rans
License: MIT
License-File: LICENSE
Keywords: HDX,country,country code,currencies,currency,exchange rate,foreign exchange,fx,iso 3166,iso2,iso3,location,region
Classifier: Development Status :: 5 - Production/Stable
Classifier: Intended Audience :: Developers
Classifier: License :: OSI Approved :: MIT License
Classifier: Natural Language :: English
Classifier: Operating System :: MacOS
Classifier: Operating System :: Microsoft :: Windows
Classifier: Operating System :: POSIX :: Linux
Classifier: Operating System :: Unix
Classifier: Programming Language :: Python
Classifier: Programming Language :: Python :: 3
Classifier: Programming Language :: Python :: 3 :: Only
Classifier: Programming Language :: Python :: 3.10
Classifier: Programming Language :: Python :: 3.11
Classifier: Programming Language :: Python :: 3.12
Classifier: Programming Language :: Python :: 3.13
Classifier: Programming Language :: Python :: 3.14
Classifier: Topic :: Software Development :: Libraries :: Python Modules
Requires-Python: >=3.10
Requires-Dist: hdx-python-utilities>=4.0.4
Requires-Dist: libhxl>=5.2.2
Requires-Dist: tenacity
Provides-Extra: docs
Requires-Dist: mkapi; extra == 'docs'
